setup.py
http_serve/__init__.py
http_serve/errors.py
http_serve/middleware.py
http_serve/request.py
http_serve/response.py
http_serve/router.py
http_serve/server.py
http_serve.egg-info/PKG-INFO
http_serve.egg-info/SOURCES.txt
http_serve.egg-info/dependency_links.txt
http_serve.egg-info/not-zip-safe
http_serve.egg-info/requires.txt
http_serve.egg-info/top_level.txt