Metadata-Version: 1.0
Name: http-serve
Version: 0.243
Summary: Minimal http service based on gevent wsgiserver
Home-page: http://wakie.com
Author: Lazarev Ivan
Author-email: lazarev.i@gmail.com
License: MIT
Platform: UNKNOWN
